aiogql/__init__.py
aiogql/client.py
aiogql/dsl.py
aiogql/gql.py
aiogql/utils.py
aiogql/transport/__init__.py
aiogql/transport/aio.py
aiogql/transport/http.py
aiogql/transport/local_schema.py
aiogql-1.1.1.dist-info/LICENSE
aiogql-1.1.1.dist-info/METADATA
aiogql-1.1.1.dist-info/WHEEL
aiogql-1.1.1.dist-info/top_level.txt
aiogql-1.1.1.dist-info/RECORD
