Metadata-Version: 2.1
Name: aiogql
Version: 1.1.1
Summary: A fork of gql which uses asyncio & aiohttp for execution
Home-page: https://github.com/cipriantarta/aiogql
Author: Ciprian Tarta
Author-email: UNKNOWN
License: MIT
Keywords: api graphql protocol rest relay gql client
Platform: UNKNOWN
Classifier: Intended Audience :: Developers
Classifier: Topic :: Software Development :: Libraries
Classifier: Programming Language :: Python :: 3.5
Classifier: Programming Language :: Python :: 3.6
Classifier: Programming Language :: Python :: Implementation :: PyPy
Requires-Dist: six (>=1.10.0)
Requires-Dist: graphql-core (<3,>=2.0)
Requires-Dist: promise (>=0.4.0)
Requires-Dist: aiohttp (>=3.1.3)
